{"name":"FolkFigur #4075579","description":"FolkFigur NFT, commissioned by Public Art Agency Sweden 2022.\n\nArtist: Ilja Karilampi; Concept software: Benoit Baudry & Martin Monperrus; Web: Viiksimaisteri; Character: Gianxmarco","image":"ipfs://QmUpwxE714v4JJvkYMj31DVGeZdiXaKHW2VR3gnDXw5KtP","external_url":"https://folkfigur.se/see/QmUpwxE714v4JJvkYMj31DVGeZdiXaKHW2VR3gnDXw5KtP","folkfigur_json":{"water":"2.4","air":"-9.6","pm25":"17.462","listens":{"song":"Fat Joe & Ashanti & Ja Rule - What's Love","int":43},"eats":{"menu":"Korvstroganoff, ris<br/>Sojakorv","int":25},"surprise":{"event":"Banarbete","int":126},"train":{"operator":"Länstrafiken Kronoberg","int":107},"elec":"19904"}}