{"name":"FolkFigur #248391","description":"FolkFigur NFT, commissioned by Public Art Agency Sweden 2022.\n\nArtist: Ilja Karilampi; Concept software: Benoit Baudry & Martin Monperrus; Web: Viiksimaisteri; Character: Gianxmarco","image":"ipfs://QmcERsXW1PSVSVzYYXvsNSLhcwfykfSZHcFrh1SqXTxRTh","external_url":"https://folkfigur.se/see/QmcERsXW1PSVSVzYYXvsNSLhcwfykfSZHcFrh1SqXTxRTh","folkfigur_json":{"water":"4.1","air":"-5.4","pm25":"4.546","listens":{"song":"Shiro - Mandana","int":82},"eats":{"menu":"Nudelwok med kyckling<br/>Wok med bönor","int":30},"surprise":{"event":"Obehöriga i spårområdet","int":63},"train":{"operator":"Öresundståg","int":76},"elec":"15143"}}