{"name":"FolkFigur #818190","description":"FolkFigur NFT, commissioned by Public Art Agency Sweden 2022.\n\nArtist: Ilja Karilampi; Concept software: Benoit Baudry & Martin Monperrus; Web: Viiksimaisteri; Character: Gianxmarco","image":"ipfs://QmbCXVhCL3zhdTs515HyzEWA5XQriupEz21WapJv5itvPk","external_url":"https://folkfigur.se/see/QmbCXVhCL3zhdTs515HyzEWA5XQriupEz21WapJv5itvPk","folkfigur_json":{"water":"2","air":"-8.5","pm25":"6.107","listens":{"song":"Lakeyah & Latto - Mind Yo Business","int":43},"eats":{"menu":"Potatisbullar/blodpudding","int":105},"surprise":{"event":"Banarbete","int":126},"train":{"operator":"Länstrafiken Kronoberg","int":107},"elec":"16943"}}