{"name":"FolkFigur #1072344","description":"FolkFigur NFT, commissioned by Public Art Agency Sweden 2022.\n\nArtist: Ilja Karilampi; Concept software: Benoit Baudry & Martin Monperrus; Web: Viiksimaisteri; Character: Gianxmarco","image":"ipfs://QmQkNX6xPpHr5GCLJ12SHj4gDKpAndjtbEWmaXkBoo6nYY","external_url":"https://folkfigur.se/see/QmQkNX6xPpHr5GCLJ12SHj4gDKpAndjtbEWmaXkBoo6nYY","folkfigur_json":{"water":"1.4","air":"-15.1","pm25":"2.251","listens":{"song":"Armani White - Billie Eilish.","int":38},"eats":{"menu":"Soppa","int":125},"surprise":{"event":"Banarbete","int":126},"train":{"operator":"Västtrafik","int":65},"elec":"18046"}}