{"name":"FolkFigur #1055087","description":"FolkFigur NFT, commissioned by Public Art Agency Sweden 2022.\n\nArtist: Ilja Karilampi; Concept software: Benoit Baudry & Martin Monperrus; Web: Viiksimaisteri; Character: Gianxmarco","image":"ipfs://QmQPcBY1YFu4DsqFr65q8aHDxwfFUB8mjLayamW6PNu8ic","external_url":"https://folkfigur.se/see/QmQPcBY1YFu4DsqFr65q8aHDxwfFUB8mjLayamW6PNu8ic","folkfigur_json":{"water":"1.4","air":"-14.6","pm25":"2.769","listens":{"song":"Sza - Shirt","int":85},"eats":{"menu":"Potatisbullar/blodpudding","int":105},"surprise":{"event":"Banarbete Ystad–Simrishamn","int":103},"train":{"operator":"Öresundståg","int":76},"elec":"22033"}}