{"name":"FolkFigur #692392","description":"FolkFigur NFT, commissioned by Public Art Agency Sweden 2022.\n\nArtist: Ilja Karilampi; Concept software: Benoit Baudry & Martin Monperrus; Web: Viiksimaisteri; Character: Gianxmarco","image":"ipfs://QmQmoVLwemCketMBa12UWPKKNY6XmUPYHTSzQv3rhUKMTQ","external_url":"https://folkfigur.se/see/QmQmoVLwemCketMBa12UWPKKNY6XmUPYHTSzQv3rhUKMTQ","folkfigur_json":{"water":"2.1","air":"-6.4","pm25":"6.496","listens":{"song":"Missy Elliott - Ching-A-Ling","int":28},"eats":{"menu":"Chili con carne, ris","int":16},"surprise":{"event":"Banarbete Mälarbanan","int":42},"train":{"operator":"Länstrafiken Kronoberg","int":107},"elec":"21196"}}