{"name":"FolkFigur #1072288","description":"FolkFigur NFT, commissioned by Public Art Agency Sweden 2022.\n\nArtist: Ilja Karilampi; Concept software: Benoit Baudry & Martin Monperrus; Web: Viiksimaisteri; Character: Gianxmarco","image":"ipfs://QmfPsCLJmeBfk9C4hYWd2w8RUd2uRjAnAqv8th5FVi8zfg","external_url":"https://folkfigur.se/see/QmfPsCLJmeBfk9C4hYWd2w8RUd2uRjAnAqv8th5FVi8zfg","folkfigur_json":{"water":"1.4","air":"-15.1","pm25":"0.42","listens":{"song":"Armani White - Billie Eilish.","int":38},"eats":{"menu":"Soppa","int":125},"surprise":{"event":"Gränskontroll Sverige–Danmark","int":121},"train":{"operator":"Öresundståg","int":76},"elec":"18031"}}