{"name":"FolkFigur #22317","description":"FolkFigur NFT, commissioned by Public Art Agency Sweden 2022.\n\nArtist: Ilja Karilampi; Concept software: Benoit Baudry & Martin Monperrus; Web: Viiksimaisteri; Character: Gianxmarco","image":"ipfs://QmczCwFkcUGBqasRJ1W6mGytk2FBnci6B7Ua5T7bcwsJNh","external_url":"https://folkfigur.se/see/QmczCwFkcUGBqasRJ1W6mGytk2FBnci6B7Ua5T7bcwsJNh","folkfigur_json":{"water":"4.3","air":"-4.4","pm25":"10.83","listens":{"song":"Wizkid - Money & Love","int":21},"eats":{"menu":"Potatis och purjolökssoppa<br/>smartfood","int":92},"surprise":{"event":"Banarbete Helsingborg","int":56},"train":{"operator":"Öresundståg","int":76},"elec":"15198"}}