{"name":"FolkFigur #54895","description":"FolkFigur NFT, commissioned by Public Art Agency Sweden 2022.\n\nArtist: Ilja Karilampi; Concept software: Benoit Baudry & Martin Monperrus; Web: Viiksimaisteri; Character: Gianxmarco","image":"ipfs://QmQhtpBZa2q1KKGw8xHf6HWooiiiq4EPSLom1cSK2j6ewy","external_url":"https://folkfigur.se/see/QmQhtpBZa2q1KKGw8xHf6HWooiiiq4EPSLom1cSK2j6ewy","folkfigur_json":{"water":"4.7","air":"-5.2","pm25":"3.659","listens":{"song":"Migos - T-Shirt","int":11},"eats":{"menu":"Fiskpanett, kall sås, potatis<br/>Veg biff","int":118},"surprise":{"event":"Banarbete Göteborg-Strömstad","int":35},"train":{"operator":"Öresundståg","int":76},"elec":"14746"}}