{"name":"FolkFigur #73324","description":"FolkFigur NFT, commissioned by Public Art Agency Sweden 2022.\n\nArtist: Ilja Karilampi; Concept software: Benoit Baudry & Martin Monperrus; Web: Viiksimaisteri; Character: Gianxmarco","image":"ipfs://QmVXJY44Gokr5hcwaeyHpdvz8b4CEgmSh17e5jWnst7ysN","external_url":"https://folkfigur.se/see/QmVXJY44Gokr5hcwaeyHpdvz8b4CEgmSh17e5jWnst7ysN","folkfigur_json":{"water":"4.6","air":"-5.2","pm25":"38.609","listens":{"song":"C.Gambino - Xxx (Bow Wow Wow)","int":63},"eats":{"menu":"Fiskpanett, kall sås, potatis<br/>Veg biff","int":118},"surprise":{"event":"Banarbete Ystad–Simrishamn","int":103},"train":{"operator":"Öresundståg","int":76},"elec":"18365"}}