{"name":"FolkFigur #74042","description":"FolkFigur NFT, commissioned by Public Art Agency Sweden 2022.\n\nArtist: Ilja Karilampi; Concept software: Benoit Baudry & Martin Monperrus; Web: Viiksimaisteri; Character: Gianxmarco","image":"ipfs://QmNRsMwy7mmKkvwk61tqPr8QZDVst2Tnep2bkPtiKsrrXB","external_url":"https://folkfigur.se/see/QmNRsMwy7mmKkvwk61tqPr8QZDVst2Tnep2bkPtiKsrrXB","folkfigur_json":{"water":"4.6","air":"-5.2","pm25":"4.793","listens":{"song":"Ken  Ring & Fre - Grabbarna Från Förorten","int":126},"eats":{"menu":"Fiskpanett, kall sås, potatis<br/>Veg biff","int":118},"surprise":{"event":"Banarbete","int":126},"train":{"operator":"SL","int":107},"elec":"18957"}}